surfdist/__init__.py
surfdist/analysis.py
surfdist/load.py
surfdist/sample.py
surfdist/utils.py
surfdist/viz.py
surfdist-0.15.5.dist-info/LICENSE.txt
surfdist-0.15.5.dist-info/METADATA
surfdist-0.15.5.dist-info/WHEEL
surfdist-0.15.5.dist-info/top_level.txt
surfdist-0.15.5.dist-info/RECORD
