Metadata-Version: 2.1
Name: surfdist
Version: 0.15.5
Summary: For calculating exact geodesic distances on cortical surface meshes
Home-page: https://github.com/NeuroanatomyAndConnectivity/surfdist
Author: Daniel Margulies
Author-email: daniel.margulies@gmail.com
License: LICENSE.txt
Keywords: geodesic,distance,brain,cortex
Platform: UNKNOWN
Requires-Python: >=3.6
Requires-Dist: Cython (>=0.29.21)
Requires-Dist: numpy (>=1.19.1)
Requires-Dist: numba (>=0.50.1)
Requires-Dist: scipy (>=1.5.2)
Requires-Dist: nibabel (>=3.1.1)
Requires-Dist: tvb-gdist (>=2.0.2)
Requires-Dist: matplotlib (>=3.3.0)
